MANIFEST.in
VERSION
requirements.txt
setup.py
src/gai_common/PDFConvert.py
src/gai_common/StatusListener.py
src/gai_common/StatusPublisher.py
src/gai_common/TextSplitter.py
src/gai_common/WSManager.py
src/gai_common/__init__.py
src/gai_common/color.py
src/gai_common/constants.py
src/gai_common/errors.py
src/gai_common/file_utils.py
src/gai_common/generators_utils.py
src/gai_common/http_utils.py
src/gai_common/image_utils.py
src/gai_common/logging.py
src/gai_common/notebook.py
src/gai_common/overlap_splitter.py
src/gai_common/sound_utils.py
src/gai_common/utils.py
src/gai_common.egg-info/PKG-INFO
src/gai_common.egg-info/SOURCES.txt
src/gai_common.egg-info/dependency_links.txt
src/gai_common.egg-info/requires.txt
src/gai_common.egg-info/top_level.txt