Metadata-Version: 2.1
Name: gai-common
Version: 0.85
Author: kakkoii1337
Author-email: kakkoii1337@gmail.com
Classifier: Programming Language :: Python :: 3.10
Classifier: Development Status :: 3 - Alpha
Classifier: License :: OSI Approved :: MIT License
Classifier: Intended Audience :: Science/Research
Classifier: Intended Audience :: Developers
Classifier: Operating System :: OS Independent
Classifier: Topic :: Software Development
Classifier: Topic :: Software Development :: Libraries :: Python Modules
Classifier: Topic :: Scientific/Engineering :: Artificial Intelligence
Requires-Python: >=3.10
Requires-Dist: pillow==10.2
Requires-Dist: markdownify
Requires-Dist: httpx
Requires-Dist: openai
Requires-Dist: python-dotenv
Requires-Dist: colorlog==6.8.2
Requires-Dist: unstructured==0.15.0
Requires-Dist: pypdf==4.3.0
Requires-Dist: rich
Requires-Dist: pynvml
